eventry/__init__.py
eventry/config.py
eventry/event.py
eventry/exceptions.py
eventry/loggers.py
eventry/py.typed
eventry/asyncio/__init__.py
eventry/asyncio/callable_wrappers.py
eventry/asyncio/default_types.py
eventry/asyncio/event.py
eventry/asyncio/filter.py
eventry/asyncio/middleware_manager.py
eventry/asyncio/dispatcher/__init__.py
eventry/asyncio/dispatcher/base.py
eventry/asyncio/dispatcher/default.py
eventry/asyncio/handler_manager/__init__.py
eventry/asyncio/handler_manager/base.py
eventry/asyncio/handler_manager/default.py
eventry/asyncio/router/__init__.py
eventry/asyncio/router/base.py
eventry/asyncio/router/default.py
eventry/sync/__init__.py
eventry-0.2.5.dist-info/METADATA
eventry-0.2.5.dist-info/WHEEL
eventry-0.2.5.dist-info/RECORD
