Metadata-Version: 2.4
Name: eventry
Version: 0.2.5
Summary: sync/async event bus implementation with no dependencies.
Project-URL: Repository, https://github.com/qvvonk/eventry
Project-URL: Issues, https://github.com/qvvonk/eventry/issues
Author-email: Qvvonk <qvvonk@gmail.com>
Maintainer-email: Qvvonk <qvvonk@gmail.com>
Classifier: Development Status :: 2 - Pre-Alpha
Classifier: Programming Language :: Python :: 3.10
Classifier: Programming Language :: Python :: 3.11
Classifier: Programming Language :: Python :: 3.12
Classifier: Programming Language :: Python :: 3.13
Classifier: Programming Language :: Python :: 3.14
Classifier: Programming Language :: Python :: 3.15
Requires-Python: >=3.10
Provides-Extra: dev
Requires-Dist: mypy>=1.17.1; extra == 'dev'
Requires-Dist: ruff; extra == 'dev'
